aifaker/__init__.py
aifaker/modules.py
aifaker-0.0.3.dist-info/METADATA
aifaker-0.0.3.dist-info/WHEEL
aifaker-0.0.3.dist-info/top_level.txt
aifaker-0.0.3.dist-info/RECORD
